[{"timestamp":"2025-09-27T01:50:40.400Z","count":0,"uniques":0},{"timestamp":"2025-09-28T02:05:05.882Z","count":0,"uniques":0},{"timestamp":"2025-09-29T01:58:48.269Z","count":0,"uniques":0},{"timestamp":"2025-09-30T01:53:31.914Z","count":0,"uniques":0},{"timestamp":"2025-10-01T02:06:11.247Z","count":0,"uniques":0},{"timestamp":"2025-10-02T01:53:52.599Z","count":0,"uniques":0},{"timestamp":"2025-10-03T01:53:34.081Z","count":0,"uniques":0},{"timestamp":"2025-10-04T01:49:13.625Z","count":0,"uniques":0}]
